eflips_schedule_rust-2.0.3.dist-info/METADATA
eflips_schedule_rust-2.0.3.dist-info/WHEEL
eflips_schedule_rust/__init__.py
eflips_schedule_rust/eflips_schedule_rust.pypy310-pp73-ppc_64-linux-gnu.so
eflips_schedule_rust-2.0.3.dist-info/RECORD
