Metadata-Version: 2.4
Name: eflips-schedule-rust
Version: 2.0.3
Classifier: Programming Language :: Rust
Classifier: Programming Language :: Python :: Implementation :: CPython
Classifier: Programming Language :: Python :: Implementation :: PyPy
Summary: Vehicle Scheduling in Rust for eFLIPS.
Author-email: Ludger Heide <ludger.heide@tu-berlin.de>
License: AGPLV3.md
Requires-Python: >=3.8
Project-URL: Repository, https://github.com/mpm-tu-berlin/eflips-schedule-rust
